{
    "name": "Delivrable",
    "fields": [
        {
            "fieldName": "name",
            "fieldType": "String",
            "fieldValidateRules": [
                "required"
            ]
        },
        {
            "fieldName": "description",
            "fieldType": "String",
            "fieldValidateRules": [
                "required"
            ]
        },
        {
            "fieldName": "target",
            "fieldType": "Instant",
            "fieldValidateRules": [
                "required"
            ]
        }
    ],
    "relationships": [
        {
            "relationshipType": "one-to-many",
            "otherEntityName": "milestone",
            "otherEntityRelationshipName": "delivrable",
            "relationshipName": "milestone"
        },
        {
            "relationshipType": "many-to-one",
            "otherEntityName": "project",
            "otherEntityRelationshipName": "delivrable",
            "relationshipName": "project",
            "otherEntityField": "id"
        }
    ],
    "changelogDate": "20190708122503",
    "entityTableName": "delivrable",
    "dto": "no",
    "pagination": "no",
    "service": "serviceClass",
    "jpaMetamodelFiltering": false,
    "fluentMethods": true,
    "clientRootFolder": "",
    "applications": "*"
}